ssh_port_forwarder/__init__.py
ssh_port_forwarder/app.py
ssh_port_forwarder-0.1.0.dist-info/METADATA
ssh_port_forwarder-0.1.0.dist-info/WHEEL
ssh_port_forwarder-0.1.0.dist-info/entry_points.txt
ssh_port_forwarder-0.1.0.dist-info/top_level.txt
ssh_port_forwarder-0.1.0.dist-info/RECORD
